pqmagic/__init__.py
pqmagic/libpqmagic_std.dll
pqmagic/pqmagic.c
pqmagic/pqmagic.cp310-win_amd64.pyd
pqmagic/pqmagic.pyx
pqmagic/pypqmagic.pxd
pqmagic/PQMagic/CMakeLists.txt
pqmagic/PQMagic/LICENSE
pqmagic/PQMagic/README.md
pqmagic/PQMagic/README_CN.md
pqmagic/PQMagic/README_EN.md
pqmagic/PQMagic/figure/PQMagic-performance-ml-dsa-87.png
pqmagic/PQMagic/figure/PQMagic-performance-ml-kem-1024.png
pqmagic/PQMagic/hash/keccak/CMakeLists.txt
pqmagic/PQMagic/hash/keccak/fips202.c
pqmagic/PQMagic/hash/keccak/fips202.h
pqmagic/PQMagic/hash/sm3/CMakeLists.txt
pqmagic/PQMagic/hash/sm3/mgf_sm3.c
pqmagic/PQMagic/hash/sm3/sm3_extended.c
pqmagic/PQMagic/hash/sm3/x86-64/Makefile
pqmagic/PQMagic/hash/sm3/x86-64/main.c
pqmagic/PQMagic/hash/sm3/x86-64/sm3.c
pqmagic/PQMagic/hash/sm3/x86-64/include/sm3.h
pqmagic/PQMagic/include/pqmagic_api.h
pqmagic/PQMagic/include/pqmagic_config.h
pqmagic/PQMagic/include/pqmagic_hash.h
pqmagic/PQMagic/include/sm3_extended.h
pqmagic/PQMagic/include/sm_config.h
pqmagic/PQMagic/kem/aigis-enc/std/CMakeLists.txt
pqmagic/PQMagic/kem/aigis-enc/std/Makefile
pqmagic/PQMagic/kem/aigis-enc/std/align.h
pqmagic/PQMagic/kem/aigis-enc/std/api.h
pqmagic/PQMagic/kem/aigis-enc/std/cbd.c
pqmagic/PQMagic/kem/aigis-enc/std/cbd.h
pqmagic/PQMagic/kem/aigis-enc/std/config.h
pqmagic/PQMagic/kem/aigis-enc/std/genmatrix.c
pqmagic/PQMagic/kem/aigis-enc/std/genmatrix.h
pqmagic/PQMagic/kem/aigis-enc/std/hashkdf.c
pqmagic/PQMagic/kem/aigis-enc/std/hashkdf.h
pqmagic/PQMagic/kem/aigis-enc/std/kem.c
pqmagic/PQMagic/kem/aigis-enc/std/ntt.c
pqmagic/PQMagic/kem/aigis-enc/std/ntt.h
pqmagic/PQMagic/kem/aigis-enc/std/owcpa.c
pqmagic/PQMagic/kem/aigis-enc/std/owcpa.h
pqmagic/PQMagic/kem/aigis-enc/std/params.h
pqmagic/PQMagic/kem/aigis-enc/std/poly.c
pqmagic/PQMagic/kem/aigis-enc/std/poly.h
pqmagic/PQMagic/kem/aigis-enc/std/polyvec.c
pqmagic/PQMagic/kem/aigis-enc/std/polyvec.h
pqmagic/PQMagic/kem/aigis-enc/std/reduce.c
pqmagic/PQMagic/kem/aigis-enc/std/reduce.h
pqmagic-1.0.4.dist-info/LICENSE.txt
pqmagic-1.0.4.dist-info/METADATA
pqmagic-1.0.4.dist-info/WHEEL
pqmagic-1.0.4.dist-info/top_level.txt
pqmagic-1.0.4.dist-info/RECORD
