Metadata-Version: 2.1
Name: pqmagic
Version: 1.0.4
Summary: The python bindings for PQMagic https://github.com/pqcrypto-cn/PQMagic
License-File: LICENSE.txt
